manim_chess/__init__.py
manim_chess/board.py
manim_chess/evaluation_bar.py
manim_chess/game_player.py
manim_chess/piece_svgs/bB.svg
manim_chess/piece_svgs/bK.svg
manim_chess/piece_svgs/bN.svg
manim_chess/piece_svgs/bP.svg
manim_chess/piece_svgs/bQ.svg
manim_chess/piece_svgs/bR.svg
manim_chess/piece_svgs/wB.svg
manim_chess/piece_svgs/wK.svg
manim_chess/piece_svgs/wN.svg
manim_chess/piece_svgs/wP.svg
manim_chess/piece_svgs/wQ.svg
manim_chess/piece_svgs/wR.svg
manim_chess/pieces.py
manim_chess-0.0.38.dist-info/LICENSE.txt
manim_chess-0.0.38.dist-info/METADATA
manim_chess-0.0.38.dist-info/WHEEL
manim_chess-0.0.38.dist-info/RECORD
