Metadata-Version: 2.3
Name: manim-chess
Version: 0.0.38
Summary: A plugin for animating chessboards. Includes additional features such as PGN conversion, arrows, etc.
Author: swoyer2
Author-email: swoyer.logan@gmail.com
Requires-Python: >=3.12
Classifier: Programming Language :: Python :: 3
Classifier: Programming Language :: Python :: 3.12
Classifier: Programming Language :: Python :: 3.13
